app/__init__.py
app/access_token.py
app/app_log.py
app/common.py
app/models.py
app/__pycache__/__init__.cpython-39.pyc
app/__pycache__/access_token.cpython-39.pyc
app/__pycache__/app_log.cpython-39.pyc
app/__pycache__/common.cpython-39.pyc
app/__pycache__/models.cpython-39.pyc
app/apiAuth/__init__.py
app/apiAuth/routes.py
app/apiAuth/__pycache__/__init__.cpython-39.pyc
app/apiAuth/__pycache__/routes.cpython-39.pyc
app/auth/__init__.py
app/auth/email.py
app/auth/forms.py
app/auth/routes.py
app/auth/__pycache__/__init__.cpython-39.pyc
app/auth/__pycache__/email.cpython-39.pyc
app/auth/__pycache__/forms.cpython-39.pyc
app/auth/__pycache__/routes.cpython-39.pyc
app/databaseManagement/__init__.py
app/databaseManagement/models.py
app/databaseManagement/routes.py
app/databaseManagement/__pycache__/__init__.cpython-39.pyc
app/databaseManagement/__pycache__/models.cpython-39.pyc
app/databaseManagement/__pycache__/routes.cpython-39.pyc
app/demo/__init__.py
app/demo/models.py
app/demo/routes.py
app/demo/__pycache__/__init__.cpython-39.pyc
app/demo/__pycache__/models.cpython-39.pyc
app/demo/__pycache__/routes.cpython-39.pyc
app/groupManagement/__init__.py
app/groupManagement/models.py
app/groupManagement/routes.py
app/groupManagement/__pycache__/__init__.cpython-39.pyc
app/groupManagement/__pycache__/models.cpython-39.pyc
app/groupManagement/__pycache__/routes.cpython-39.pyc
app/main/__init__.py
app/main/apirequest.py
app/main/db2.py
app/main/db_base.py
app/main/db_connections.py
app/main/dbexec.py
app/main/forms.py
app/main/mariadb.py
app/main/mssql.py
app/main/mysql.py
app/main/oracle.py
app/main/oracle_origin.py
app/main/postgresql.py
app/main/routes.py
app/main/saved_queries.py
app/main/sqlite.py
app/main/sybase.py
app/main/__pycache__/__init__.cpython-39.pyc
app/main/__pycache__/apirequest.cpython-39.pyc
app/main/__pycache__/db2.cpython-39.pyc
app/main/__pycache__/db_base.cpython-39.pyc
app/main/__pycache__/db_connections.cpython-39.pyc
adj_dataparrots_3-0.0.4.dist-info/METADATA
adj_dataparrots_3-0.0.4.dist-info/WHEEL
adj_dataparrots_3-0.0.4.dist-info/top_level.txt
adj_dataparrots_3-0.0.4.dist-info/RECORD
